README.md
agents_collector/__init__.py
agents_collector/cli/__init__.py
agents_collector/cli/cli_main.py
agents_collector/config/__init__.py
agents_collector/config/config_manager.py
agents_collector/fetcher/__init__.py
agents_collector/fetcher/github_fetcher.py
agents_collector/parser/__init__.py
agents_collector/parser/index_parser.py
agents_collector/ui/__init__.py
agents_collector/ui/interactive_selector.py
agent_fetch-0.1.0.dist-info/METADATA
agent_fetch-0.1.0.dist-info/WHEEL
agent_fetch-0.1.0.dist-info/entry_points.txt
agent_fetch-0.1.0.dist-info/RECORD
