Metadata-Version: 2.4
Name: agent-fetch
Version: 0.1.0
Summary: CLI tool for fetching AGENTS.md files from GitHub
Project-URL: Repository, https://github.com/FreeMarketamilitia/agent-fetch
Author: FreeMarketamilitia
Maintainer: FreeMarketaMilitia
License: MIT
Keywords: agents,cli,documentation,fetch,github
Classifier: Development Status :: 4 - Beta
Classifier: Intended Audience :: Developers
Classifier: License :: OSI Approved :: MIT License
Classifier: Operating System :: OS Independent
Classifier: Programming Language :: Python :: 3
Classifier: Programming Language :: Python :: 3.9
Classifier: Programming Language :: Python :: 3.10
Classifier: Programming Language :: Python :: 3.11
Classifier: Programming Language :: Python :: 3.12
Classifier: Programming Language :: Python :: 3.13
Classifier: Topic :: Utilities
Requires-Python: >=3.9
Requires-Dist: pyyaml>=6.0.0
Requires-Dist: questionary>=2.0.0
Requires-Dist: rapidfuzz>=3.0.0
Requires-Dist: requests>=2.31.0
Requires-Dist: rich>=13.0.0
Requires-Dist: typer>=0.9.0
